dedscumulus/RequestHandler.py
dedscumulus/SharePointHandler.py
dedscumulus/TableLogHandler.py
dedscumulus/__init__.py
dedscumulus/brzGlobal.py
dedscumulus/gbtGlobal.py
dedscumulus/mstAst.py
dedscumulus/mstLog.py
src/RequestHandler.py
src/SharePointHandler.py
src/TableLogHandler.py
src/__init__.py
src/brzGlobal.py
src/gbtGlobal.py
src/mstAst.py
src/mstLog.py
dedscumulus-0.1.0.dist-info/LICENSE
dedscumulus-0.1.0.dist-info/METADATA
dedscumulus-0.1.0.dist-info/WHEEL
dedscumulus-0.1.0.dist-info/top_level.txt
dedscumulus-0.1.0.dist-info/RECORD
