Metadata-Version: 2.1
Name: dedscumulus
Version: 0.1.0
Summary: Kernel functions for Cumulus
Home-page: https://github.com/nino-baywa/dedscumulus
Author: BayWa r.e. Data Services GmbH
Author-email: no-reply@baywa-re.com
License: UNKNOWN
Project-URL: repository, https://github.com/nino-baywa/dedscumulus
Platform: UNKNOWN
Classifier: Programming Language :: Python :: 3
Classifier: Operating System :: OS Independent
Requires-Python: >=3.8
License-File: LICENSE
